{
  data: [
    {
      "x": [10, 10],
      "y": [-14.2375467738113, 32.3759074986423],
      "text": "xintercept: 10",
      "type": "scatter",
      "mode": "lines",
      "line": {
        "width": 1.88976377952756,
        "color": "rgba(0,0,0,1)",
        "dash": "dash"
      },
      "hoveron": "points",
      "showlegend": false,
      "xaxis": "x",
      "yaxis": "y",
      "hoverinfo": "text",
      "frame": null
    },
    {
      "x": [10, 10],
      "y": [-14.2375467738113, 32.3759074986423],
      "text": "xintercept: 10",
      "type": "scatter",
      "mode": "lines",
      "line": {
        "width": 1.88976377952756,
        "color": "rgba(0,0,0,1)",
        "dash": "dash"
      },
      "hoveron": "points",
      "showlegend": false,
      "xaxis": "x2",
      "yaxis": "y",
      "hoverinfo": "text",
      "frame": null
    },
    {
      "x": [10, 10],
      "y": [-14.2375467738113, 32.3759074986423],
      "text": "xintercept: 10",
      "type": "scatter",
      "mode": "lines",
      "line": {
        "width": 1.88976377952756,
        "color": "rgba(0,0,0,1)",
        "dash": "dash"
      },
      "hoveron": "points",
      "showlegend": false,
      "xaxis": "x3",
      "yaxis": "y",
      "hoverinfo": "text",
      "frame": null
    },
    {
      "x": [10, 10],
      "y": [-14.2375467738113, 32.3759074986423],
      "text": "xintercept: 10",
      "type": "scatter",
      "mode": "lines",
      "line": {
        "width": 1.88976377952756,
        "color": "rgba(0,0,0,1)",
        "dash": "dash"
      },
      "hoveron": "points",
      "showlegend": false,
      "xaxis": "x4",
      "yaxis": "y",
      "hoverinfo": "text",
      "frame": null
    },
    {
      "x": [-0.318753873342648, 23.2948559496272],
      "y": [-0.318753873342648, 23.2948559496272],
      "text": "intercept: 0<br />slope: 1",
      "type": "scatter",
      "mode": "lines",
      "line": {
        "width": 1.88976377952756,
        "color": "rgba(0,0,0,1)",
        "dash": "dashdot"
      },
      "hoveron": "points",
      "showlegend": false,
      "xaxis": "x",
      "yaxis": "y",
      "hoverinfo": "text",
      "frame": null
    },
    {
      "x": [-0.318753873342648, 23.2948559496272],
      "y": [-0.318753873342648, 23.2948559496272],
      "text": "intercept: 0<br />slope: 1",
      "type": "scatter",
      "mode": "lines",
      "line": {
        "width": 1.88976377952756,
        "color": "rgba(0,0,0,1)",
        "dash": "dashdot"
      },
      "hoveron": "points",
      "showlegend": false,
      "xaxis": "x2",
      "yaxis": "y",
      "hoverinfo": "text",
      "frame": null
    },
    {
      "x": [-0.318753873342648, 23.2948559496272],
      "y": [-0.318753873342648, 23.2948559496272],
      "text": "intercept: 0<br />slope: 1",
      "type": "scatter",
      "mode": "lines",
      "line": {
        "width": 1.88976377952756,
        "color": "rgba(0,0,0,1)",
        "dash": "dashdot"
      },
      "hoveron": "points",
      "showlegend": false,
      "xaxis": "x3",
      "yaxis": "y",
      "hoverinfo": "text",
      "frame": null
    },
    {
      "x": [-0.318753873342648, 23.2948559496272],
      "y": [-0.318753873342648, 23.2948559496272],
      "text": "intercept: 0<br />slope: 1",
      "type": "scatter",
      "mode": "lines",
      "line": {
        "width": 1.88976377952756,
        "color": "rgba(0,0,0,1)",
        "dash": "dashdot"
      },
      "hoveron": "points",
      "showlegend": false,
      "xaxis": "x4",
      "yaxis": "y",
      "hoverinfo": "text",
      "frame": null
    },
    {
      "x": [-0.318753873342648, 23.2948559496272],
      "y": [-0.159376936671324, 11.6474279748136],
      "text": "yint: 0<br />slope: 0.5",
      "type": "scatter",
      "mode": "lines",
      "line": {
        "width": 1.88976377952756,
        "color": "rgba(0,100,0,1)",
        "dash": "solid"
      },
      "hoveron": "points",
      "showlegend": false,
      "xaxis": "x",
      "yaxis": "y",
      "hoverinfo": "text",
      "frame": null
    },
    {
      "x": [-0.318753873342648, 23.2948559496272],
      "y": [-0.223127711339854, 16.3063991647391],
      "text": "yint: 0<br />slope: 0.7",
      "type": "scatter",
      "mode": "lines",
      "line": {
        "width": 1.88976377952756,
        "color": "rgba(0,0,255,1)",
        "dash": "solid"
      },
      "hoveron": "points",
      "showlegend": false,
      "xaxis": "x2",
      "yaxis": "y",
      "hoverinfo": "text",
      "frame": null
    },
    {
      "x": [-0.318753873342648, 23.2948559496272],
      "y": [-0.318753873342648, 23.2948559496272],
      "text": "yint: 0<br />slope: 1.0",
      "type": "scatter",
      "mode": "lines",
      "line": {
        "width": 1.88976377952756,
        "color": "rgba(160,32,240,1)",
        "dash": "solid"
      },
      "hoveron": "points",
      "showlegend": false,
      "xaxis": "x3",
      "yaxis": "y",
      "hoverinfo": "text",
      "frame": null
    },
    {
      "x": [-0.318753873342648, 23.2948559496272],
      "y": [-0.318753873342648, 23.2948559496272],
      "text": "yint: 0<br />slope: 1.0",
      "type": "scatter",
      "mode": "lines",
      "line": {
        "width": 1.88976377952756,
        "color": "rgba(160,32,240,1)",
        "dash": "solid"
      },
      "hoveron": "points",
      "showlegend": false,
      "xaxis": "x4",
      "yaxis": "y",
      "hoverinfo": "text",
      "frame": null
    },
    {
      "x": [2.76172217149287],
      "y": [2.92780102444813],
      "text": "Distance:  3<br />Yards_gained:   3<br />Play_type: Fumble Recovery (Own)<br />Success: Successful",
      "type": "scatter",
      "mode": "markers",
      "marker": {
        "autocolorscale": false,
        "color": "rgba(0,100,0,1)",
        "opacity": 1,
        "size": 11.3385826771654,
        "symbol": "circle",
        "line": {
          "width": 1.88976377952756,
          "color": "rgba(0,100,0,1)"
        }
      },
      "hoveron": "points",
      "name": "(Successful,Fumble Recovery (Own))",
      "legendgroup": "(Successful,Fumble Recovery (Own))",
      "showlegend": true,
      "xaxis": "x3",
      "yaxis": "y",
      "hoverinfo": "text",
      "frame": null
    },
    {
      "x": [14.7019679836929, 10.3371766518801],
      "y": [14.0479056249838, 10.0999504562933],
      "text": ["Distance: 15<br />Yards_gained:  14<br />Play_type: Pass Reception<br />Success: Successful", "Distance: 10<br />Yards_gained:  10<br />Play_type: Pass Reception<br />Success: Successful"],
      "type": "scatter",
      "mode": "markers",
      "marker": {
        "autocolorscale": false,
        "color": "rgba(0,100,0,1)",
        "opacity": 1,
        "size": 11.3385826771654,
        "symbol": "triangle-up",
        "line": {
          "width": 1.88976377952756,
          "color": "rgba(0,100,0,1)"
        }
      },
      "hoveron": "points",
      "name": "(Successful,Pass Reception)",
      "legendgroup": "(Successful,Pass Reception)",
      "showlegend": true,
      "xaxis": "x",
      "yaxis": "y",
      "hoverinfo": "text",
      "frame": null
    },
    {
      "x": [4.80835325233638, 4.88285834118724, 8.80625662337989, 10.7900262568146, 4.39357845913619, 8.27591078206897],
      "y": [5.97824108772911, 5.95187700069509, 8.06063395524398, 20.7733968118206, 3.16864343206398, 12.029067998752],
      "text": ["Distance:  5<br />Yards_gained:   6<br />Play_type: Pass Reception<br />Success: Successful", "Distance:  5<br />Yards_gained:   6<br />Play_type: Pass Reception<br />Success: Successful", "Distance:  9<br />Yards_gained:   8<br />Play_type: Pass Reception<br />Success: Successful", "Distance: 11<br />Yards_gained:  21<br />Play_type: Pass Reception<br />Success: Successful", "Distance:  4<br />Yards_gained:   3<br />Play_type: Pass Reception<br />Success: Successful", "Distance:  8<br />Yards_gained:  12<br />Play_type: Pass Reception<br />Success: Successful"],
      "type": "scatter",
      "mode": "markers",
      "marker": {
        "autocolorscale": false,
        "color": "rgba(0,100,0,1)",
        "opacity": 1,
        "size": 11.3385826771654,
        "symbol": "triangle-up",
        "line": {
          "width": 1.88976377952756,
          "color": "rgba(0,100,0,1)"
        }
      },
      "hoveron": "points",
      "name": "(Successful,Pass Reception)",
      "legendgroup": "(Successful,Pass Reception)",
      "showlegend": false,
      "xaxis": "x2",
      "yaxis": "y",
      "hoverinfo": "text",
      "frame": null
    },
    {
      "x": [2.20497799981385, 1.13633196111768],
      "y": [3.99193262411281, 6.79643229912035],
      "text": ["Distance:  2<br />Yards_gained:   4<br />Play_type: Pass Reception<br />Success: Successful", "Distance:  1<br />Yards_gained:   7<br />Play_type: Pass Reception<br />Success: Successful"],
      "type": "scatter",
      "mode": "markers",
      "marker": {
        "autocolorscale": false,
        "color": "rgba(0,100,0,1)",
        "opacity": 1,
        "size": 11.3385826771654,
        "symbol": "triangle-up",
        "line": {
          "width": 1.88976377952756,
          "color": "rgba(0,100,0,1)"
        }
      },
      "hoveron": "points",
      "name": "(Successful,Pass Reception)",
      "legendgroup": "(Successful,Pass Reception)",
      "showlegend": false,
      "xaxis": "x3",
      "yaxis": "y",
      "hoverinfo": "text",
      "frame": null
    },
    {
      "x": [6.87610526103526],
      "y": [6.79568792046048],
      "text": "Distance:  7<br />Yards_gained:   7<br />Play_type: Passing Touchdown<br />Success: Successful",
      "type": "scatter",
      "mode": "markers",
      "marker": {
        "autocolorscale": false,
        "color": "rgba(0,100,0,1)",
        "opacity": 1,
        "size": 11.3385826771654,
        "symbol": "square-open-dot",
        "line": {
          "width": 1.88976377952756,
          "color": "rgba(0,100,0,1)"
        }
      },
      "hoveron": "points",
      "name": "(Successful,Passing Touchdown)",
      "legendgroup": "(Successful,Passing Touchdown)",
      "showlegend": true,
      "xaxis": "x3",
      "yaxis": "y",
      "hoverinfo": "text",
      "frame": null
    },
    {
      "x": [10.3994796406478, 9.91523292530328, 9.83186610545963, 10.3293896419927, 9.62639040704817, 9.72151113916189],
      "y": [5.11857502893545, 6.034770943271, 8.83139673233964, 4.99442922845483, 10.8319510614034, 5.81860918547027],
      "text": ["Distance: 10<br />Yards_gained:   5<br />Play_type: Rush<br />Success: Successful", "Distance: 10<br />Yards_gained:   6<br />Play_type: Rush<br />Success: Successful", "Distance: 10<br />Yards_gained:   9<br />Play_type: Rush<br />Success: Successful", "Distance: 10<br />Yards_gained:   5<br />Play_type: Rush<br />Success: Successful", "Distance: 10<br />Yards_gained:  11<br />Play_type: Rush<br />Success: Successful", "Distance: 10<br />Yards_gained:   6<br />Play_type: Rush<br />Success: Successful"],
      "type": "scatter",
      "mode": "markers",
      "marker": {
        "autocolorscale": false,
        "color": "rgba(0,100,0,1)",
        "opacity": 1,
        "size": 11.3385826771654,
        "symbol": "circle",
        "line": {
          "width": 1.88976377952756,
          "color": "rgba(0,100,0,1)"
        }
      },
      "hoveron": "points",
      "name": "(Successful,Rush)",
      "legendgroup": "(Successful,Rush)",
      "showlegend": true,
      "xaxis": "x",
      "yaxis": "y",
      "hoverinfo": "text",
      "frame": null
    },
    {
      "x": [1.39676514901221, 8.17780775614083],
      "y": [1.18013349385001, 5.96125175831839],
      "text": ["Distance:  1<br />Yards_gained:   1<br />Play_type: Rush<br />Success: Successful", "Distance:  8<br />Yards_gained:   6<br />Play_type: Rush<br />Success: Successful"],
      "type": "scatter",
      "mode": "markers",
      "marker": {
        "autocolorscale": false,
        "color": "rgba(0,100,0,1)",
        "opacity": 1,
        "size": 11.3385826771654,
        "symbol": "circle",
        "line": {
          "width": 1.88976377952756,
          "color": "rgba(0,100,0,1)"
        }
      },
      "hoveron": "points",
      "name": "(Successful,Rush)",
      "legendgroup": "(Successful,Rush)",
      "showlegend": false,
      "xaxis": "x2",
      "yaxis": "y",
      "hoverinfo": "text",
      "frame": null
    },
    {
      "x": [1.36696815546602, 0.754592027701438, 2.02656486723572],
      "y": [30.2571141226217, 2.72160767591558, 3.2064505525399],
      "text": ["Distance:  1<br />Yards_gained:  30<br />Play_type: Rush<br />Success: Successful", "Distance:  1<br />Yards_gained:   3<br />Play_type: Rush<br />Success: Successful", "Distance:  2<br />Yards_gained:   3<br />Play_type: Rush<br />Success: Successful"],
      "type": "scatter",
      "mode": "markers",
      "marker": {
        "autocolorscale": false,
        "color": "rgba(0,100,0,1)",
        "opacity": 1,
        "size": 11.3385826771654,
        "symbol": "circle",
        "line": {
          "width": 1.88976377952756,
          "color": "rgba(0,100,0,1)"
        }
      },
      "hoveron": "points",
      "name": "(Successful,Rush)",
      "legendgroup": "(Successful,Rush)",
      "showlegend": false,
      "xaxis": "x3",
      "yaxis": "y",
      "hoverinfo": "text",
      "frame": null
    },
    {
      "x": [8.75896849501878],
      "y": [-4.9698697689455],
      "text": "Distance:  9<br />Yards_gained:  -5<br />Play_type: Fumble Recovery (Own)<br />Success: Unsuccessful",
      "type": "scatter",
      "mode": "markers",
      "marker": {
        "autocolorscale": false,
        "color": "rgba(139,26,26,1)",
        "opacity": 1,
        "size": 11.3385826771654,
        "symbol": "circle",
        "line": {
          "width": 1.88976377952756,
          "color": "rgba(139,26,26,1)"
        }
      },
      "hoveron": "points",
      "name": "(Unsuccessful,Fumble Recovery (Own))",
      "legendgroup": "(Unsuccessful,Fumble Recovery (Own))",
      "showlegend": true,
      "xaxis": "x2",
      "yaxis": "y",
      "hoverinfo": "text",
      "frame": null
    },
    {
      "x": [10.2649345288053],
      "y": [-0.164374790433794],
      "text": "Distance: 10<br />Yards_gained:   0<br />Play_type: Interception<br />Success: Unsuccessful",
      "type": "scatter",
      "mode": "markers",
      "marker": {
        "autocolorscale": false,
        "color": "rgba(139,26,26,1)",
        "opacity": 1,
        "size": 11.3385826771654,
        "symbol": "cross-thin-open",
        "line": {
          "width": 1.88976377952756,
          "color": "rgba(139,26,26,1)"
        }
      },
      "hoveron": "points",
      "name": "(Unsuccessful,Interception)",
      "legendgroup": "(Unsuccessful,Interception)",
      "showlegend": true,
      "xaxis": "x",
      "yaxis": "y",
      "hoverinfo": "text",
      "frame": null
    },
    {
      "x": [10.2527627063915, 9.3185517122969, 9.91568585392088],
      "y": [-0.176946917222813, -0.182707671448588, 0.203761413367465],
      "text": ["Distance: 10<br />Yards_gained:   0<br />Play_type: Pass Incompletion<br />Success: Unsuccessful", "Distance:  9<br />Yards_gained:   0<br />Play_type: Pass Incompletion<br />Success: Unsuccessful", "Distance: 10<br />Yards_gained:   0<br />Play_type: Pass Incompletion<br />Success: Unsuccessful"],
      "type": "scatter",
      "mode": "markers",
      "marker": {
        "autocolorscale": false,
        "color": "rgba(139,26,26,1)",
        "opacity": 1,
        "size": 11.3385826771654,
        "symbol": "triangle-up-open",
        "line": {
          "width": 1.88976377952756,
          "color": "rgba(139,26,26,1)"
        }
      },
      "hoveron": "points",
      "name": "(Unsuccessful,Pass Incompletion)",
      "legendgroup": "(Unsuccessful,Pass Incompletion)",
      "showlegend": true,
      "xaxis": "x",
      "yaxis": "y",
      "hoverinfo": "text",
      "frame": null
    },
    {
      "x": [1.32218839004636, 11.6954182650894],
      "y": [-0.0338271050713956, -0.126642986107618],
      "text": ["Distance:  1<br />Yards_gained:   0<br />Play_type: Pass Incompletion<br />Success: Unsuccessful", "Distance: 12<br />Yards_gained:   0<br />Play_type: Pass Incompletion<br />Success: Unsuccessful"],
      "type": "scatter",
      "mode": "markers",
      "marker": {
        "autocolorscale": false,
        "color": "rgba(139,26,26,1)",
        "opacity": 1,
        "size": 11.3385826771654,
        "symbol": "triangle-up-open",
        "line": {
          "width": 1.88976377952756,
          "color": "rgba(139,26,26,1)"
        }
      },
      "hoveron": "points",
      "name": "(Unsuccessful,Pass Incompletion)",
      "legendgroup": "(Unsuccessful,Pass Incompletion)",
      "showlegend": false,
      "xaxis": "x2",
      "yaxis": "y",
      "hoverinfo": "text",
      "frame": null
    },
    {
      "x": [14.9434236465022, 7.81815751474351, 13.9775252221152, 22.2215100485831, 6.35823291838169],
      "y": [0.0141544357873499, 0.0371020698454231, -0.258103010756895, -0.0639379536733031, -0.241888219909742],
      "text": ["Distance: 15<br />Yards_gained:   0<br />Play_type: Pass Incompletion<br />Success: Unsuccessful", "Distance:  8<br />Yards_gained:   0<br />Play_type: Pass Incompletion<br />Success: Unsuccessful", "Distance: 14<br />Yards_gained:   0<br />Play_type: Pass Incompletion<br />Success: Unsuccessful", "Distance: 22<br />Yards_gained:   0<br />Play_type: Pass Incompletion<br />Success: Unsuccessful", "Distance:  6<br />Yards_gained:   0<br />Play_type: Pass Incompletion<br />Success: Unsuccessful"],
      "type": "scatter",
      "mode": "markers",
      "marker": {
        "autocolorscale": false,
        "color": "rgba(139,26,26,1)",
        "opacity": 1,
        "size": 11.3385826771654,
        "symbol": "triangle-up-open",
        "line": {
          "width": 1.88976377952756,
          "color": "rgba(139,26,26,1)"
        }
      },
      "hoveron": "points",
      "name": "(Unsuccessful,Pass Incompletion)",
      "legendgroup": "(Unsuccessful,Pass Incompletion)",
      "showlegend": false,
      "xaxis": "x3",
      "yaxis": "y",
      "hoverinfo": "text",
      "frame": null
    },
    {
      "x": [15.1851088475436, 10.0882412774488, 9.67553468961269, 9.76502256374806, 9.91909220330417],
      "y": [3.02881386475638, 3.89548228392378, 0.927323637204245, 2.9152833390981, 1.06853738152422],
      "text": ["Distance: 15<br />Yards_gained:   3<br />Play_type: Pass Reception<br />Success: Unsuccessful", "Distance: 10<br />Yards_gained:   4<br />Play_type: Pass Reception<br />Success: Unsuccessful", "Distance: 10<br />Yards_gained:   1<br />Play_type: Pass Reception<br />Success: Unsuccessful", "Distance: 10<br />Yards_gained:   3<br />Play_type: Pass Reception<br />Success: Unsuccessful", "Distance: 10<br />Yards_gained:   1<br />Play_type: Pass Reception<br />Success: Unsuccessful"],
      "type": "scatter",
      "mode": "markers",
      "marker": {
        "autocolorscale": false,
        "color": "rgba(139,26,26,1)",
        "opacity": 1,
        "size": 11.3385826771654,
        "symbol": "triangle-up",
        "line": {
          "width": 1.88976377952756,
          "color": "rgba(139,26,26,1)"
        }
      },
      "hoveron": "points",
      "name": "(Unsuccessful,Pass Reception)",
      "legendgroup": "(Unsuccessful,Pass Reception)",
      "showlegend": true,
      "xaxis": "x",
      "yaxis": "y",
      "hoverinfo": "text",
      "frame": null
    },
    {
      "x": [9.96635517627001, 12.3249372564256, 19.2396961471066, 6.05426263846457, 7.29373644553125, 6.87624155767262],
      "y": [-0.0955770498141646, 4.29342502825893, 8.71829592674039, 4.24163727788255, 1.8925813511014, 4.28971224455163],
      "text": ["Distance: 10<br />Yards_gained:   0<br />Play_type: Pass Reception<br />Success: Unsuccessful", "Distance: 12<br />Yards_gained:   4<br />Play_type: Pass Reception<br />Success: Unsuccessful", "Distance: 19<br />Yards_gained:   9<br />Play_type: Pass Reception<br />Success: Unsuccessful", "Distance:  6<br />Yards_gained:   4<br />Play_type: Pass Reception<br />Success: Unsuccessful", "Distance:  7<br />Yards_gained:   2<br />Play_type: Pass Reception<br />Success: Unsuccessful", "Distance:  7<br />Yards_gained:   4<br />Play_type: Pass Reception<br />Success: Unsuccessful"],
      "type": "scatter",
      "mode": "markers",
      "marker": {
        "autocolorscale": false,
        "color": "rgba(139,26,26,1)",
        "opacity": 1,
        "size": 11.3385826771654,
        "symbol": "triangle-up",
        "line": {
          "width": 1.88976377952756,
          "color": "rgba(139,26,26,1)"
        }
      },
      "hoveron": "points",
      "name": "(Unsuccessful,Pass Reception)",
      "legendgroup": "(Unsuccessful,Pass Reception)",
      "showlegend": false,
      "xaxis": "x2",
      "yaxis": "y",
      "hoverinfo": "text",
      "frame": null
    },
    {
      "x": [8.7404636695981],
      "y": [2.76963702952489],
      "text": "Distance:  9<br />Yards_gained:   3<br />Play_type: Pass Reception<br />Success: Unsuccessful",
      "type": "scatter",
      "mode": "markers",
      "marker": {
        "autocolorscale": false,
        "color": "rgba(139,26,26,1)",
        "opacity": 1,
        "size": 11.3385826771654,
        "symbol": "triangle-up",
        "line": {
          "width": 1.88976377952756,
          "color": "rgba(139,26,26,1)"
        }
      },
      "hoveron": "points",
      "name": "(Unsuccessful,Pass Reception)",
      "legendgroup": "(Unsuccessful,Pass Reception)",
      "showlegend": false,
      "xaxis": "x3",
      "yaxis": "y",
      "hoverinfo": "text",
      "frame": null
    },
    {
      "x": [9.8686968177557, 9.71558502689004, 10.0113916764036, 10.2093767905608, 7.62937227580696, 10.0523723389953, 10.131167039834],
      "y": [1.77441536616534, 2.29461328973994, 1.13360603661276, 2.21078030047938, 0.0526500582229346, 2.72474915357307, 1.86439288416877],
      "text": ["Distance: 10<br />Yards_gained:   2<br />Play_type: Rush<br />Success: Unsuccessful", "Distance: 10<br />Yards_gained:   2<br />Play_type: Rush<br />Success: Unsuccessful", "Distance: 10<br />Yards_gained:   1<br />Play_type: Rush<br />Success: Unsuccessful", "Distance: 10<br />Yards_gained:   2<br />Play_type: Rush<br />Success: Unsuccessful", "Distance:  8<br />Yards_gained:   0<br />Play_type: Rush<br />Success: Unsuccessful", "Distance: 10<br />Yards_gained:   3<br />Play_type: Rush<br />Success: Unsuccessful", "Distance: 10<br />Yards_gained:   2<br />Play_type: Rush<br />Success: Unsuccessful"],
      "type": "scatter",
      "mode": "markers",
      "marker": {
        "autocolorscale": false,
        "color": "rgba(139,26,26,1)",
        "opacity": 1,
        "size": 11.3385826771654,
        "symbol": "circle",
        "line": {
          "width": 1.88976377952756,
          "color": "rgba(139,26,26,1)"
        }
      },
      "hoveron": "points",
      "name": "(Unsuccessful,Rush)",
      "legendgroup": "(Unsuccessful,Rush)",
      "showlegend": true,
      "xaxis": "x",
      "yaxis": "y",
      "hoverinfo": "text",
      "frame": null
    },
    {
      "x": [8.15880078822374, 7.97253392338753, 11.0104006480426],
      "y": [1.82622719858773, 1.18966155340895, 1.99688829276711],
      "text": ["Distance:  8<br />Yards_gained:   2<br />Play_type: Rush<br />Success: Unsuccessful", "Distance:  8<br />Yards_gained:   1<br />Play_type: Rush<br />Success: Unsuccessful", "Distance: 11<br />Yards_gained:   2<br />Play_type: Rush<br />Success: Unsuccessful"],
      "type": "scatter",
      "mode": "markers",
      "marker": {
        "autocolorscale": false,
        "color": "rgba(139,26,26,1)",
        "opacity": 1,
        "size": 11.3385826771654,
        "symbol": "circle",
        "line": {
          "width": 1.88976377952756,
          "color": "rgba(139,26,26,1)"
        }
      },
      "hoveron": "points",
      "name": "(Unsuccessful,Rush)",
      "legendgroup": "(Unsuccessful,Rush)",
      "showlegend": false,
      "xaxis": "x2",
      "yaxis": "y",
      "hoverinfo": "text",
      "frame": null
    },
    {
      "x": [12.1493552435189, 13.7190671158955],
      "y": [3.02641802569851, 3.84830808364786],
      "text": ["Distance: 12<br />Yards_gained:   3<br />Play_type: Rush<br />Success: Unsuccessful", "Distance: 14<br />Yards_gained:   4<br />Play_type: Rush<br />Success: Unsuccessful"],
      "type": "scatter",
      "mode": "markers",
      "marker": {
        "autocolorscale": false,
        "color": "rgba(139,26,26,1)",
        "opacity": 1,
        "size": 11.3385826771654,
        "symbol": "circle",
        "line": {
          "width": 1.88976377952756,
          "color": "rgba(139,26,26,1)"
        }
      },
      "hoveron": "points",
      "name": "(Unsuccessful,Rush)",
      "legendgroup": "(Unsuccessful,Rush)",
      "showlegend": false,
      "xaxis": "x3",
      "yaxis": "y",
      "hoverinfo": "text",
      "frame": null
    },
    {
      "x": [10.3502395404503],
      "y": [-12.1187533977907],
      "text": "Distance: 10<br />Yards_gained: -12<br />Play_type: Sack<br />Success: Unsuccessful",
      "type": "scatter",
      "mode": "markers",
      "marker": {
        "autocolorscale": false,
        "color": "rgba(139,26,26,1)",
        "opacity": 1,
        "size": 11.3385826771654,
        "symbol": "triangle-down-open",
        "line": {
          "width": 1.88976377952756,
          "color": "rgba(139,26,26,1)"
        }
      },
      "hoveron": "points",
      "name": "(Unsuccessful,Sack)",
      "legendgroup": "(Unsuccessful,Sack)",
      "showlegend": true,
      "xaxis": "x2",
      "yaxis": "y",
      "hoverinfo": "text",
      "frame": null
    },
    {
      "x": [10.314867855981],
      "y": [-7.98238106071949],
      "text": "Distance: 10<br />Yards_gained:  -8<br />Play_type: Sack<br />Success: Unsuccessful",
      "type": "scatter",
      "mode": "markers",
      "marker": {
        "autocolorscale": false,
        "color": "rgba(139,26,26,1)",
        "opacity": 1,
        "size": 11.3385826771654,
        "symbol": "triangle-down-open",
        "line": {
          "width": 1.88976377952756,
          "color": "rgba(139,26,26,1)"
        }
      },
      "hoveron": "points",
      "name": "(Unsuccessful,Sack)",
      "legendgroup": "(Unsuccessful,Sack)",
      "showlegend": false,
      "xaxis": "x3",
      "yaxis": "y",
      "hoverinfo": "text",
      "frame": null
    },
    {
      "x": [null, null, null, null, null],
      "y": [15, null, null, 15, 15],
      "text": "",
      "type": "scatter",
      "mode": "lines",
      "line": {
        "width": 1.88976377952756,
        "color": "transparent",
        "dash": "solid"
      },
      "fill": "toself",
      "fillcolor": "rgba(255,48,48,0.2)",
      "hoveron": "fills",
      "showlegend": false,
      "xaxis": "x",
      "yaxis": "y",
      "hoverinfo": "text",
      "frame": null
    },
    {
      "x": [null, null, null, null, null],
      "y": [15, null, null, 15, 15],
      "text": "",
      "type": "scatter",
      "mode": "lines",
      "line": {
        "width": 1.88976377952756,
        "color": "transparent",
        "dash": "solid"
      },
      "fill": "toself",
      "fillcolor": "rgba(255,48,48,0.2)",
      "hoveron": "fills",
      "showlegend": false,
      "xaxis": "x2",
      "yaxis": "y",
      "hoverinfo": "text",
      "frame": null
    },
    {
      "x": [null, null, null, null, null],
      "y": [15, null, null, 15, 15],
      "text": "",
      "type": "scatter",
      "mode": "lines",
      "line": {
        "width": 1.88976377952756,
        "color": "transparent",
        "dash": "solid"
      },
      "fill": "toself",
      "fillcolor": "rgba(255,48,48,0.2)",
      "hoveron": "fills",
      "showlegend": false,
      "xaxis": "x3",
      "yaxis": "y",
      "hoverinfo": "text",
      "frame": null
    },
    {
      "x": [null, null, null, null, null],
      "y": [15, null, null, 15, 15],
      "text": "",
      "type": "scatter",
      "mode": "lines",
      "line": {
        "width": 1.88976377952756,
        "color": "transparent",
        "dash": "solid"
      },
      "fill": "toself",
      "fillcolor": "rgba(255,48,48,0.2)",
      "hoveron": "fills",
      "showlegend": false,
      "xaxis": "x4",
      "yaxis": "y",
      "hoverinfo": "text",
      "frame": null
    },
    {
      "x": [null, null, null, null, null],
      "y": [null, 0, 0, null, null],
      "text": "",
      "type": "scatter",
      "mode": "lines",
      "line": {
        "width": 1.88976377952756,
        "color": "transparent",
        "dash": "solid"
      },
      "fill": "toself",
      "fillcolor": "rgba(153,153,153,0.2)",
      "hoveron": "fills",
      "showlegend": false,
      "xaxis": "x",
      "yaxis": "y",
      "hoverinfo": "text",
      "frame": null
    },
    {
      "x": [null, null, null, null, null],
      "y": [null, 0, 0, null, null],
      "text": "",
      "type": "scatter",
      "mode": "lines",
      "line": {
        "width": 1.88976377952756,
        "color": "transparent",
        "dash": "solid"
      },
      "fill": "toself",
      "fillcolor": "rgba(153,153,153,0.2)",
      "hoveron": "fills",
      "showlegend": false,
      "xaxis": "x2",
      "yaxis": "y",
      "hoverinfo": "text",
      "frame": null
    },
    {
      "x": [null, null, null, null, null],
      "y": [null, 0, 0, null, null],
      "text": "",
      "type": "scatter",
      "mode": "lines",
      "line": {
        "width": 1.88976377952756,
        "color": "transparent",
        "dash": "solid"
      },
      "fill": "toself",
      "fillcolor": "rgba(153,153,153,0.2)",
      "hoveron": "fills",
      "showlegend": false,
      "xaxis": "x3",
      "yaxis": "y",
      "hoverinfo": "text",
      "frame": null
    },
    {
      "x": [null, null, null, null, null],
      "y": [null, 0, 0, null, null],
      "text": "",
      "type": "scatter",
      "mode": "lines",
      "line": {
        "width": 1.88976377952756,
        "color": "transparent",
        "dash": "solid"
      },
      "fill": "toself",
      "fillcolor": "rgba(153,153,153,0.2)",
      "hoveron": "fills",
      "showlegend": false,
      "xaxis": "x4",
      "yaxis": "y",
      "hoverinfo": "text",
      "frame": null
    }
  ],
  layout: {
    "margin": {
      "t": 54.9649923896499,
      "r": 7.30593607305936,
      "b": 39.6955859969559,
      "l": 43.1050228310502
    },
    "plot_bgcolor": "rgba(229,229,229,1)",
    "paper_bgcolor": "rgba(255,255,255,1)",
    "font": {
      "color": "rgba(0,0,0,1)",
      "family": "",
      "size": 14.6118721461187
    },
    "title": {
      "text": "Middle Tennessee[7]: Yards to be Successful vs Yards gained by Down  (Color lines = success, Dot-dash line = 1st down)<br> <sup>2023: wk01 vs Alabama[56]<\/sup>",
      "font": {
        "color": "rgba(0,0,0,1)",
        "family": "",
        "size": 17.5342465753425
      },
      "x": 0,
      "xref": "paper",
      "xanchor": "left"
    },
    "xaxis": {
      "domain": [0, 0.241438356164384],
      "automargin": true,
      "type": "linear",
      "autorange": false,
      "range": [-0.318753873342648, 23.2948559496272],
      "tickmode": "array",
      "ticktext": ["0", "2", "4", "6", "8", "10", "12", "14", "16", "18", "20", "22"],
      "tickvals": [0, 2, 4, 6, 8, 10, 12, 14, 16, 18, 20, 22],
      "categoryorder": "array",
      "categoryarray": ["0", "2", "4", "6", "8", "10", "12", "14", "16", "18", "20", "22"],
      "nticks": null,
      "ticks": "outside",
      "tickcolor": "rgba(51,51,51,1)",
      "ticklen": 3.65296803652968,
      "tickwidth": 0.66417600664176,
      "showticklabels": true,
      "tickfont": {
        "color": "rgba(77,77,77,1)",
        "family": "",
        "size": 11.689497716895
      },
      "tickangle": -0,
      "showline": false,
      "linecolor": null,
      "linewidth": 0,
      "showgrid": true,
      "gridcolor": "rgba(204,204,204,1)",
      "gridwidth": 0.66417600664176,
      "zeroline": false,
      "anchor": "y",
      "title": "",
      "hoverformat": ".2f"
    },
    "annotations": [
      {
        "text": "Distance to 1st down or TD",
        "x": 0.5,
        "y": 0,
        "showarrow": false,
        "ax": 0,
        "ay": 0,
        "font": {
          "color": "rgba(0,0,0,1)",
          "family": "",
          "size": 14.6118721461187
        },
        "xref": "paper",
        "yref": "paper",
        "textangle": -0,
        "xanchor": "center",
        "yanchor": "top",
        "annotationType": "axis",
        "yshift": -21.9178082191781
      },
      {
        "text": "Yards gained",
        "x": 0,
        "y": 0.5,
        "showarrow": false,
        "ax": 0,
        "ay": 0,
        "font": {
          "color": "rgba(0,0,0,1)",
          "family": "",
          "size": 14.6118721461187
        },
        "xref": "paper",
        "yref": "paper",
        "textangle": -90,
        "xanchor": "right",
        "yanchor": "center",
        "annotationType": "axis",
        "xshift": -27.7625570776256
      },
      {
        "text": "1st Down <br />Total: 24 = Suc: 8 + Unsuc: 16, TD/1st: 2",
        "x": 0.120719178082192,
        "y": 1,
        "showarrow": false,
        "ax": 0,
        "ay": 0,
        "font": {
          "color": "rgba(26,26,26,1)",
          "family": "",
          "size": 11.689497716895
        },
        "xref": "paper",
        "yref": "paper",
        "textangle": -0,
        "xanchor": "center",
        "yanchor": "bottom"
      },
      {
        "text": "2nd Down <br />Total: 21 = Suc: 8 + Unsuc: 13, TD/1st: 5",
        "x": 0.375,
        "y": 1,
        "showarrow": false,
        "ax": 0,
        "ay": 0,
        "font": {
          "color": "rgba(26,26,26,1)",
          "family": "",
          "size": 11.689497716895
        },
        "xref": "paper",
        "yref": "paper",
        "textangle": -0,
        "xanchor": "center",
        "yanchor": "bottom"
      },
      {
        "text": "3rd Down <br />Total: 16 = Suc: 7 + Unsuc: 9, TD/1st: 7",
        "x": 0.625,
        "y": 1,
        "showarrow": false,
        "ax": 0,
        "ay": 0,
        "font": {
          "color": "rgba(26,26,26,1)",
          "family": "",
          "size": 11.689497716895
        },
        "xref": "paper",
        "yref": "paper",
        "textangle": -0,
        "xanchor": "center",
        "yanchor": "bottom"
      },
      {
        "text": "4th Down <br />Total: 0 = Suc: 0 + Unsuc: 0, TD/1st: 0",
        "x": 0.879280821917808,
        "y": 1,
        "showarrow": false,
        "ax": 0,
        "ay": 0,
        "font": {
          "color": "rgba(26,26,26,1)",
          "family": "",
          "size": 11.689497716895
        },
        "xref": "paper",
        "yref": "paper",
        "textangle": -0,
        "xanchor": "center",
        "yanchor": "bottom"
      }
    ],
    "yaxis": {
      "domain": [0, 1],
      "automargin": true,
      "type": "linear",
      "autorange": false,
      "range": [-14.2375467738113, 32.3759074986423],
      "tickmode": "array",
      "ticktext": ["-10", "-5", "0", "5", "10", "15", "20", "25", "30"],
      "tickvals": [-10, -5, -1.77635683940025e-15, 5, 10, 15, 20, 25, 30],
      "categoryorder": "array",
      "categoryarray": ["-10", "-5", "0", "5", "10", "15", "20", "25", "30"],
      "nticks": null,
      "ticks": "outside",
      "tickcolor": "rgba(51,51,51,1)",
      "ticklen": 3.65296803652968,
      "tickwidth": 0.66417600664176,
      "showticklabels": true,
      "tickfont": {
        "color": "rgba(77,77,77,1)",
        "family": "",
        "size": 11.689497716895
      },
      "tickangle": -0,
      "showline": false,
      "linecolor": null,
      "linewidth": 0,
      "showgrid": true,
      "gridcolor": "rgba(204,204,204,1)",
      "gridwidth": 0.66417600664176,
      "zeroline": false,
      "anchor": "x",
      "title": "",
      "hoverformat": ".2f"
    },
    "shapes": [
      {
        "type": "rect",
        "fillcolor": null,
        "line": {
          "color": null,
          "width": 0,
          "linetype": []
        },
        "yref": "paper",
        "xref": "paper",
        "x0": 0,
        "x1": 0.241438356164384,
        "y0": 0,
        "y1": 1
      },
      {
        "type": "rect",
        "fillcolor": "rgba(217,217,217,1)",
        "line": {
          "color": "transparent",
          "width": 0.66417600664176,
          "linetype": "solid"
        },
        "yref": "paper",
        "xref": "paper",
        "x0": 0,
        "x1": 0.241438356164384,
        "y0": 0,
        "y1": 23.37899543379,
        "yanchor": 1,
        "ysizemode": "pixel"
      },
      {
        "type": "rect",
        "fillcolor": null,
        "line": {
          "color": null,
          "width": 0,
          "linetype": []
        },
        "yref": "paper",
        "xref": "paper",
        "x0": 0.258561643835616,
        "x1": 0.491438356164384,
        "y0": 0,
        "y1": 1
      },
      {
        "type": "rect",
        "fillcolor": "rgba(217,217,217,1)",
        "line": {
          "color": "transparent",
          "width": 0.66417600664176,
          "linetype": "solid"
        },
        "yref": "paper",
        "xref": "paper",
        "x0": 0.258561643835616,
        "x1": 0.491438356164384,
        "y0": 0,
        "y1": 23.37899543379,
        "yanchor": 1,
        "ysizemode": "pixel"
      },
      {
        "type": "rect",
        "fillcolor": null,
        "line": {
          "color": null,
          "width": 0,
          "linetype": []
        },
        "yref": "paper",
        "xref": "paper",
        "x0": 0.508561643835616,
        "x1": 0.741438356164384,
        "y0": 0,
        "y1": 1
      },
      {
        "type": "rect",
        "fillcolor": "rgba(217,217,217,1)",
        "line": {
          "color": "transparent",
          "width": 0.66417600664176,
          "linetype": "solid"
        },
        "yref": "paper",
        "xref": "paper",
        "x0": 0.508561643835616,
        "x1": 0.741438356164384,
        "y0": 0,
        "y1": 23.37899543379,
        "yanchor": 1,
        "ysizemode": "pixel"
      },
      {
        "type": "rect",
        "fillcolor": null,
        "line": {
          "color": null,
          "width": 0,
          "linetype": []
        },
        "yref": "paper",
        "xref": "paper",
        "x0": 0.758561643835616,
        "x1": 1,
        "y0": 0,
        "y1": 1
      },
      {
        "type": "rect",
        "fillcolor": "rgba(217,217,217,1)",
        "line": {
          "color": "transparent",
          "width": 0.66417600664176,
          "linetype": "solid"
        },
        "yref": "paper",
        "xref": "paper",
        "x0": 0.758561643835616,
        "x1": 1,
        "y0": 0,
        "y1": 23.37899543379,
        "yanchor": 1,
        "ysizemode": "pixel"
      }
    ],
    "xaxis2": {
      "type": "linear",
      "autorange": false,
      "range": [-0.318753873342648, 23.2948559496272],
      "tickmode": "array",
      "ticktext": ["0", "2", "4", "6", "8", "10", "12", "14", "16", "18", "20", "22"],
      "tickvals": [0, 2, 4, 6, 8, 10, 12, 14, 16, 18, 20, 22],
      "categoryorder": "array",
      "categoryarray": ["0", "2", "4", "6", "8", "10", "12", "14", "16", "18", "20", "22"],
      "nticks": null,
      "ticks": "outside",
      "tickcolor": "rgba(51,51,51,1)",
      "ticklen": 3.65296803652968,
      "tickwidth": 0.66417600664176,
      "showticklabels": true,
      "tickfont": {
        "color": "rgba(77,77,77,1)",
        "family": "",
        "size": 11.689497716895
      },
      "tickangle": -0,
      "showline": false,
      "linecolor": null,
      "linewidth": 0,
      "showgrid": true,
      "domain": [0.258561643835616, 0.491438356164384],
      "gridcolor": "rgba(204,204,204,1)",
      "gridwidth": 0.66417600664176,
      "zeroline": false,
      "anchor": "y",
      "title": "",
      "hoverformat": ".2f"
    },
    "xaxis3": {
      "type": "linear",
      "autorange": false,
      "range": [-0.318753873342648, 23.2948559496272],
      "tickmode": "array",
      "ticktext": ["0", "2", "4", "6", "8", "10", "12", "14", "16", "18", "20", "22"],
      "tickvals": [0, 2, 4, 6, 8, 10, 12, 14, 16, 18, 20, 22],
      "categoryorder": "array",
      "categoryarray": ["0", "2", "4", "6", "8", "10", "12", "14", "16", "18", "20", "22"],
      "nticks": null,
      "ticks": "outside",
      "tickcolor": "rgba(51,51,51,1)",
      "ticklen": 3.65296803652968,
      "tickwidth": 0.66417600664176,
      "showticklabels": true,
      "tickfont": {
        "color": "rgba(77,77,77,1)",
        "family": "",
        "size": 11.689497716895
      },
      "tickangle": -0,
      "showline": false,
      "linecolor": null,
      "linewidth": 0,
      "showgrid": true,
      "domain": [0.508561643835616, 0.741438356164384],
      "gridcolor": "rgba(204,204,204,1)",
      "gridwidth": 0.66417600664176,
      "zeroline": false,
      "anchor": "y",
      "title": "",
      "hoverformat": ".2f"
    },
    "xaxis4": {
      "type": "linear",
      "autorange": false,
      "range": [-0.318753873342648, 23.2948559496272],
      "tickmode": "array",
      "ticktext": ["0", "2", "4", "6", "8", "10", "12", "14", "16", "18", "20", "22"],
      "tickvals": [0, 2, 4, 6, 8, 10, 12, 14, 16, 18, 20, 22],
      "categoryorder": "array",
      "categoryarray": ["0", "2", "4", "6", "8", "10", "12", "14", "16", "18", "20", "22"],
      "nticks": null,
      "ticks": "outside",
      "tickcolor": "rgba(51,51,51,1)",
      "ticklen": 3.65296803652968,
      "tickwidth": 0.66417600664176,
      "showticklabels": true,
      "tickfont": {
        "color": "rgba(77,77,77,1)",
        "family": "",
        "size": 11.689497716895
      },
      "tickangle": -0,
      "showline": false,
      "linecolor": null,
      "linewidth": 0,
      "showgrid": true,
      "domain": [0.758561643835616, 1],
      "gridcolor": "rgba(204,204,204,1)",
      "gridwidth": 0.66417600664176,
      "zeroline": false,
      "anchor": "y",
      "title": "",
      "hoverformat": ".2f"
    },
    "showlegend": true,
    "legend": {
      "bgcolor": "rgba(255,255,255,1)",
      "bordercolor": "transparent",
      "borderwidth": 1.88976377952756,
      "font": {
        "color": "rgba(0,0,0,1)",
        "family": "",
        "size": 11.689497716895
      },
      "title": {
        "text": "Success<br />Play type",
        "font": {
          "color": "rgba(0,0,0,1)",
          "family": "",
          "size": 14.6118721461187
        }
      }
    },
    "hovermode": "closest",
    "barmode": "relative"
  },
  config: {
    "doubleClick": "reset",
    "modeBarButtonsToAdd": ["hoverclosest", "hovercompare"],
    "showSendToCloud": false
  },
  source: "A",
  attrs: {
    "5a9015203ca": {
      "xintercept": {},
      "type": "scatter"
    },
    "5a903749fd3": {
      "intercept": {},
      "slope": {}
    },
    "5a901e084f24": {
      "intercept": {},
      "slope": {}
    },
    "5a9024ae6a70": {
      "x": {},
      "y": {},
      "shape": {},
      "colour": {}
    },
    "5a901a9b7780": {
      "xmin": {},
      "xmax": {},
      "ymin": {},
      "ymax": {}
    },
    "5a904f3c3e07": {
      "xmin": {},
      "xmax": {},
      "ymin": {},
      "ymax": {}
    }
  },
  cur_data: "5a9015203ca",
  visdat: {
    "5a9015203ca": ["function (y) ", "x"],
    "5a903749fd3": ["function (y) ", "x"],
    "5a901e084f24": ["function (y) ", "x"],
    "5a9024ae6a70": ["function (y) ", "x"],
    "5a901a9b7780": ["function (y) ", "x"],
    "5a904f3c3e07": ["function (y) ", "x"]
  },
  highlight: {
    "on": "plotly_click",
    "persistent": false,
    "dynamic": false,
    "selectize": false,
    "opacityDim": 0.2,
    "selected": {
      "opacity": 1
    },
    "debounce": 0
  },
  shinyEvents: ["plotly_hover", "plotly_click", "plotly_selected", "plotly_relayout", "plotly_brushed", "plotly_brushing", "plotly_clickannotation", "plotly_doubleclick", "plotly_deselect", "plotly_afterplot", "plotly_sunburstclick"],
  base_url: "https://plot.ly"
}